{
    "title": "Градивне именице",
    "description": "",
    "topic":"66d8df3890dfd493a4175613",
    "type":"лекција",
    "contentBlocks": [
        
        
        {
            "type": "text",
            "textBlock": {
                "content":"НОВА КУЋА",
                "style": {
                    "fontSize": 24,
                    "color": "#000000",
                    "bold": false,
                    "italic": false
                },
                "position": 1
            }
        }
        ,
        {
            "type": "text",
            "textBlock": {
                "content":"Мој деда Петар је одлучио да у свом дворишту сагради нову кућу. Сви смо се радовали. Деда је грађевински радник и предводиће екипу која ће бити на градилишту. Организовао је довоз грађевинског материјала и распоредио раднике. Из камиона су истоварени: <b>песак</b>, <b>камен</b> <b>креч</b>, <b>дрво</b>, <b>цигла</b> и <b>гвожђе</b>. Почела је градња. Радници су ископали темељ, ставили <b>гвожђе</b> и већу количину смеше од <b>шљунка</b>, <b>цемента</b> и <b>воде</b>. Градња је настављена <b>циглом</b>. Кућа је брзо саграђена и усељена.",
                "style": {
                    "fontSize": 24,
                    "color": "#000000",
                    "bold": false,
                    "italic": false
                },
                "position": 1
            }
        }
        ,
        {
            "type": "text",
            "textBlock": {
                "content":"У наведеном тексту истакнуте су збирне именице: <b>цвеће</b>, <b>дрвеће</b>, <b>одећа</b>, <b>лишће</b>, <b>жбуње</b> и <b>грање</b>. Оне означавају збир (мноштво) нечега што припада истој врсти и чини једну целину. Ако је пред нама збир бића и предмета, мноштво у коме се они не могу пребројати, онда употребљавамо збирну именицу.",
                "style": {
                    "fontSize": 24,
                    "color": "#000000",
                    "bold": false,
                    "italic": false
                },
                "position": 1
            }
        },
        {
            "type": "text",
            "textBlock": {
                "content":"У тексту су подебљане градивне именице: <b>песак</b>, <b>камен</b>, <b>креч</b>, <b>дрво</b>, <b>цигла</b>, <b>гвожђе</b>, <b>шљунак</b>, <b>цемент</b> и <b>вода</b>. Градивне именице означавају неку материју (грађу) и гласе исто кад означавају најмању и највећу количину. <br>Обликом једнине градивне именице означавају сваку, па и највећу, количину материје.",
                "style": {
                    "fontSize": 24,
                    "color": "#000000",
                    "bold": false,
                    "italic": false
                },
                "position": 1
            }
        },
        {
            "type": "text",
            "textBlock": {
                "content":"-Ми правимо дворац од песка.<br>-Овде има много песка.<br>-У кантици има мало песка.<br>",
                "style": {
                    "fontSize": 24,
                    "color": "#000000",
                    "bold": false,
                    "italic": false
                },
                "position": 1
            }
        },
        {
            "type": "question",
            "questionBlock":{
                "questionType":"true_false",
                "question":"Градивне именице могу означавати и најмању и највећу количину материје, а облик именице остаје исти.",
                "type":"граматика",
                "tags":["именице","градивне именице"],
                "grade":3,
                "correctAnswer":true
            }
        },
        {
            "type": "question",
            "questionBlock":{
                "questionType":"classic",
                "question":"Која реч у следећој реченици представља градивну именицу?\n „Радници су ископали темељ и ставили већу количину шљунка.“",
                "tags":["именице","градивне именице"],
                "type":"граматика",
                "grade":3,
                "correctAnswers":["шљунак","шљунка"]

            }
        },
        {
            "type": "question",
            "questionBlock":{
                "questionType":"multiple_choice",
                "question":"Која од следећих именица је градивна?",
                "options":["кућа", "вода","цвет"],
                "type":"граматика",
                "tags":["именице","градивне именице"],
                "grade":3,
                "correctAnswerMC":"вода"
            }
        },
        {
            "type": "question",
            "questionBlock":{
                "questionType":"multiple_choice",
                "question":"Која од следећих именица је градивна?",
                "options":["цигла", "чаша","цвет"],
                "type":"граматика",
                "tags":["именице","градивне именице"],
                "grade":3,
                "correctAnswerMC":"цигла"
            }
        },
        {
            "type": "question",
            "questionBlock":{
                "questionType":"multiple_choice",
                "question":"Која од следећих именица је градивна?",
                "options":["лопта", "камен","мачка"],
                "type":"граматика",
                "tags":["именице","градивне именице"],
                "grade":3,
                "correctAnswerMC":"камен"
            }
        },
        {
            "type": "question",
            "questionBlock":{
                "questionType":"multiple_choice",
                "question":"У којој форми се најчешће користе градивне именице?",
                "options":["у множини","у једнини"],
                "type":"граматика",
                "tags":["именице","градивне именице"],
                "grade":3,
                "correctAnswerMC":"у једнини"
            }
        }
    ]}